precisiondoc/__init__.py
precisiondoc/main.py
precisiondoc/ai/__init__.py
precisiondoc/ai/ai_client.py
precisiondoc/ai/qwen_api.py
precisiondoc/config/__init__.py
precisiondoc/config/document_format_settings.py
precisiondoc/config/promptes.py
precisiondoc/pdf/__init__.py
precisiondoc/pdf/pdf_processor.py
precisiondoc/pdf/pdf_utils.py
precisiondoc/utils/__init__.py
precisiondoc/utils/data_utils.py
precisiondoc/utils/log_utils.py
precisiondoc/utils/word_utils.py
precisiondoc/utils/word/__init__.py
precisiondoc/utils/word/content_formatting.py
precisiondoc/utils/word/document_formatting.py
precisiondoc/utils/word/evidence_processing.py
precisiondoc/utils/word/export_utils.py
precisiondoc/utils/word/image_utils.py
precisiondoc/utils/word/table_utils.py
precisiondoc-0.1.3.dist-info/licenses/LICENSE
precisiondoc-0.1.3.dist-info/METADATA
precisiondoc-0.1.3.dist-info/WHEEL
precisiondoc-0.1.3.dist-info/entry_points.txt
precisiondoc-0.1.3.dist-info/top_level.txt
precisiondoc-0.1.3.dist-info/RECORD
