Metadata-Version: 2.4
Name: precisiondoc
Version: 0.1.3
Summary: Document processing and evidence extraction package for precision oncology
Home-page: https://github.com/kaychiao/precisiondoc
Author: Kay Chiao
Author-email: Kay Chiao <kaychiao216@gmail.com>
License: MIT
Classifier: Programming Language :: Python :: 3
Classifier: License :: OSI Approved :: MIT License
Classifier: Operating System :: OS Independent
Requires-Python: >=3.8
License-File: LICENSE
Requires-Dist: PyMuPDF>=1.24.11
Requires-Dist: openai==1.96.1
Requires-Dist: requests==2.31.0
Requires-Dist: pandas<2.4.0,>=1.5.3
Requires-Dist: python-dotenv==1.0.0
Requires-Dist: python-docx>=1.1.2
Requires-Dist: openpyxl>=3.1.5
Requires-Dist: numpy<2.4.0,>=1.24.0
Requires-Dist: tqdm>=4.67.1
Requires-Dist: pillow>=8.2.0
Dynamic: author
Dynamic: home-page
Dynamic: license-file
Dynamic: requires-python
